[
  {
    "id": "25c0752d-9eb4-422b-8ff2-689da408f866",
    "scheme_url": "https://pbscfc.punjab.gov.in/?q=node/26",
    "title": "ELIGIBILITY:-",
    "description": "The Corporation started a schemes for the benefit of beneficiaries with the assistance of NSFDC from the year 1990-91, in view of acute shortage of the share capital.\n\nELIGIBILITY:-\n\n      1.The beneficiary should be from the Scheduled Castes Community.\n\n      2.Up to RS. 3.00 lakhs for both Rural and Urban areas. At least 50% of funding to the beneficiaries having annual family income up to Rs. 1.50 lakh and balance 50% funding to the beneficiaries having annual family income above Rs. 1.50 lakh and up to Rs. 3.00 Lakh.\n\nFUNDING PATTERN:-\nThe Corporation raises term loan from NSFDC for specific schemes for onward disbursement to the beneficiaries. The NSFDC share is Up To 90% of the total unit cost and the remaining 10% is shared by the beneficiary as well as Corporation out of share capital depending upon the terms and conditions of the NSFDC and state govt.\n\nSUBSIDY:-\nScheduled Castes living below the poverty line are eligible for subsidy Up To 10,000/-.\n\nPROCEDURE FOR TAKING LOAN:-\nAny Scheduled Caste person desirous of availing loan can apply on the prescribed application form available free of cost from District offices. Application duly attested is to be submitted to the Distt. Offices. Then cases are referred to screening committee for scrutiny .Cases are then sent to the Head Office for sanction. After that cases are sent to District offices for execution of Mortgage deed .There after payment is made subject to completion of all formalities.",
    "ELIGIBILITY": "",
    "FUNDING PATTERN": "The Corporation raises term loan from NSFDC for specific schemes for onward disbursement to the beneficiaries. The NSFDC share is Up To 90% of the total unit cost and the remaining 10% is shared by the beneficiary as well as Corporation out of share capital depending upon the terms and conditions of the NSFDC and state govt.",
    "SUBSIDY": "Scheduled Castes living below the poverty line are eligible for subsidy Up To 10,000/-.",
    "SOURCES OF FUNDS": "",
    "REPAYMENT": "",
    "RATE OF INTEREST": "",
    "PROCEDURE FOR TAKING LOAN": "Any Scheduled Caste person desirous of availing loan can apply on the prescribed application form available free of cost from District offices. Application duly attested is to be submitted to the Distt. Offices. Then cases are referred to screening committee for scrutiny .Cases are then sent to the Head Office for sanction. After that cases are sent to District offices for execution of Mortgage deed .There after payment is made subject to completion of all formalities.",
    "Description": "The Corporation started a schemes for the benefit of beneficiaries with the assistance of NSFDC from the year 1990-91, in view of acute shortage of the share capital. 1.The beneficiary should be from the Scheduled Castes Community. 2.Up to RS. 3.00 lakhs for both Rural and Urban areas. At least 50% of funding to the beneficiaries having annual family income up to Rs. 1.50 lakh and balance 50% funding to the beneficiaries having annual family income above Rs. 1.50 lakh and up to Rs. 3.00 Lakh."
  },
  {
    "id": "a3e4c431-9ab5-4997-895f-ec6e7ac1cd87",
    "scheme_url": "https://pbscfc.punjab.gov.in/?q=node/29",
    "title": "ELIGIBILITY:-",
    "description": "This corporation is advancing loans to Safai Karamcharis and their dependents by raising term loan from NSKFDC from the year 2002-03 onwards.\n\nELIGIBILITY:-\nAny Safai Karamchari or his dependent is eligible for availing loan.\n\nFUNDING PATTERN:-\nThe Corporation raises term loan from NSKFDC @ 3%  for specific schemes for onwards disbursement to the beneficiaries @ 6% NSKFDC share is Up To 90% and remaining amount would be contributed by corporation and Loanee.\n\nPROCEDURE FOR TAKING LOAN:-\n\nAny safai karamcharis or his dependent person desirous of availing loan can apply on the prescribed application form available free of cost from District offices. Application duly attested is to be submitted to the Distt. Offices . Then cases are referred to screening committee under the chairmanship ADC (D) for scrutiny .Cases are then sent to the Head Office for sanction. After that cases are sent to District offices for execution of Mortgage deed .There after payment is made directly to bank a/c of loaness through RTGS subject to completion of all formalities",
    "ELIGIBILITY": "Any Safai Karamchari or his dependent is eligible for availing loan.",
    "FUNDING PATTERN": "The Corporation raises term loan from NSKFDC @ 3% &nbsp;for specific schemes for onwards disbursement to the beneficiaries @ 6% NSKFDC share is Up To 90% and remaining amount would be contributed by corporation and Loanee.",
    "SUBSIDY": "",
    "SOURCES OF FUNDS": "",
    "REPAYMENT": "",
    "RATE OF INTEREST": "",
    "PROCEDURE FOR TAKING LOAN": "",
    "Description": "This corporation is advancing loans to Safai Karamcharis and their dependents by raising term loan from NSKFDC from the year 2002-03 onwards. Any safai karamcharis or his dependent person desirous of availing loan can apply on the prescribed application form available free of cost from District offices. Application duly attested is to be submitted to the Distt. Offices . Then cases are referred to screening committee under the chairmanship ADC (D) for scrutiny .Cases are then sent to the Head Office for sanction. After that cases are sent to District offices for execution of Mortgage deed .There after payment is made directly to bank a/c of loaness through RTGS subject to completion of all formalities"
  },
  {
    "id": "0cbb07bf-952f-42b0-a541-ddb8554500e5",
    "scheme_url": "https://pbscfc.punjab.gov.in/?q=node/165",
    "title": "DIRECT LENDING SCHEME",
    "description": "DIRECT LENDING SCHEME\n\nThe Corporation is providing Loans Directly for Economic up-liftment of the members of the Scheduled Castes and handicapped people in the State of Punjab.\n\nELIGIBILITY:-\nAny scheduled caste person between the age of 18 years to 55 years residing in Punjab is eligible to avail loan under this scheme. Under this schemes income limit is Rs.1.00 Lacs but at time of considering the loan case of the applicant, his annual income from all sources would be taken into consideration. However, if a prospective beneficiary is otherwise un-employed and intends to start his own business his family income may not be taken into consideration.\n\nFUNDING  PATTERN:-\nDifferent amounts of loans are advanced depending upon the purpose of the unit to be established. Maximum loan limit is Rs.10.00 Lacs, except Land purchase where maximum limit is Rs.30.00 Lacs.\n\nSUBSIDY:-\nBelow Poverty Line Scheduled Castes loanees are eligible for subsidy of special central Assistances @ 50% of loan amount or RS 10000/- whichever is less.\n\nSOURCES OF FUNDS:-\nShare Capital Funds\n\nREPAYMENT:-\nPeriod varies according to the kind of the project with monthly, bimonthly, quarterly or half yearly installments with maximum period of repayment of 15 years for land purchase cases.\n\nRATE OF INTEREST:-\nRate of interest Up To 50,000/- @ 5% and above 50,000/- @8%. Penal Interest @ 5% is charged for delayed payment/ non-repayment/violation of terms and conditions of loan.\n\nPROCEDURE FOR TAKING LOAN:-\nAny Scheduled Caste person desirous of availing loan can apply on the prescribed application form available free of cost from District offices. Application duly attested is to be submitted to the Distt. Offices . Then cases are referred to screening committee under the chairmanship of ADC (D) for scrutiny .Cases are then sent to the Head Office for sanction. After sanction the cases are sent to District offices for execution of Mortgage Deed. Thereafter payment is made subject to completion of all formalities from H.O. into the Bank A/C of loanee directly through RTGS.\n\nAnnexure mentioning Purposes and Loan details under Direct Lending Scheme",
    "ELIGIBILITY": "Any scheduled caste person between the age of 18 years to 55 years residing in Punjab is eligible to avail loan under this scheme. Under this schemes income limit is Rs.1.00 Lacs but at time of considering the loan case of the applicant, his annual income from all sources would be taken into consideration. However, if a prospective beneficiary is otherwise un-employed and intends to start his own business his family income may not be taken into consideration.",
    "FUNDING PATTERN": "",
    "SUBSIDY": "Below Poverty Line Scheduled Castes loanees are eligible for subsidy of special central Assistances @ 50% of loan amount or RS 10000/- whichever is less.",
    "SOURCES OF FUNDS": "Share Capital Funds",
    "REPAYMENT": "Period varies according to the kind of the project with monthly, bimonthly, quarterly or half yearly installments with maximum period of repayment of 15 years for land purchase cases.",
    "RATE OF INTEREST": "Rate of interest Up To 50,000/- @ 5% and above 50,000/- @8%. Penal Interest @ 5% is charged for delayed payment/ non-repayment/violation of terms and conditions of loan.",
    "PROCEDURE FOR TAKING LOAN": "Any Scheduled Caste person desirous of availing loan can apply on the prescribed application form available free of cost from District offices. Application duly attested is to be submitted to the Distt. Offices . Then cases are referred to screening committee under the chairmanship of ADC (D) for scrutiny .Cases are then sent to the Head Office for sanction. After sanction the cases are sent to District offices for execution of Mortgage Deed. Thereafter payment is made subject to completion of all formalities from H.O. into the Bank A/C of loanee directly through RTGS.",
    "Description": "The Corporation is providing Loans Directly for Economic up-liftment of the members of the Scheduled Castes and handicapped people in the State of Punjab. Different amounts of loans are advanced depending upon the purpose of the unit to be established. Maximum loan limit is Rs.10.00 Lacs, except Land purchase where maximum limit is Rs.30.00 Lacs. Annexure mentioning Purposes and Loan details under Direct Lending Scheme"
  },
  {
    "id": "c05cfe22-106e-4a82-b312-c5d59762cf0f",
    "scheme_url": "https://pbscfc.punjab.gov.in/?q=node/25",
    "title": "Under this scheme, Loans are arranged through banks and subsidy is provided by the Corporation.",
    "description": "Under this scheme, Loans are arranged through banks and subsidy is provided by the Corporation.\nELIGIBILITY:\nPersons belonging to scheduled castes living below poverty line are eligible under this scheme. (For rural areas Rs.67649/- P.A. and for urban areas Rs.88756/- P.A. per family)\nFUNDING PATTERN:\nThe loan is provided by the banks as per their norms.\n\nSUBSIDY:\nCapital subsidy Up To 50% of the total amount subject to\nmaximum of Rs.10000/-.\n\nSOURCES OF FUNDS:-\nSubsidy:\nSubsidy is provided by Govt. of India out of SCA.\n\nLoan:\nThe loan amount is provided by various banks operating in the State. Rate of interest changed by the Banks as per RBI guidelines.\n\nProcedure for taking loan:\nApplicants desirous of availing loan can apply on the prescribed application form specified for the scheme, available at the District offices free of cost. There after application complete in all respect is to be submitted in the District office Then the District Manager sponsor the application to the concerned bank branch for joint verification .Cases are sanctioned & subsidy is claimed by the banks. Then these cases are referred to the District level committee chaired by the ADC. The loan is disbursed to the beneficiaries by the banks along with subsidy.",
    "ELIGIBILITY": "Persons belonging to scheduled castes living below poverty line are eligible under this scheme. (For rural areas Rs.67649/- P.A. and for urban areas Rs.88756/- P.A. per family)",
    "FUNDING PATTERN": "The loan is provided by the banks as per their norms.",
    "SUBSIDY": "Capital subsidy Up To 50% of the total amount subject to\nmaximum of Rs.10000/-.",
    "SOURCES OF FUNDS": "Subsidy:\nSubsidy is provided by Govt. of India out of SCA.",
    "REPAYMENT": "",
    "RATE OF INTEREST": "",
    "PROCEDURE FOR TAKING LOAN": "Applicants desirous of availing loan can apply on the prescribed application form specified for the scheme, available at the District offices free of cost. There after application complete in all respect is to be submitted in the District office Then the District Manager sponsor the application to the concerned bank branch for joint verification .Cases are sanctioned &amp; subsidy is claimed by the banks. Then these cases are referred to the District level committee chaired by the ADC. The loan is disbursed to the beneficiaries by the banks along with subsidy.",
    "Description": "The loan amount is provided by various banks operating in the State. Rate of interest changed by the Banks as per RBI guidelines."
  }
]